telealchemy/__init__.py
telealchemy/core.py
telealchemy/core_mysql.py
telealchemy/core_postgres.py
telealchemy/core_sqlite.py
telealchemy/orm.py
telealchemy/sqlalchemy.py
telealchemy-1.0.3.dist-info/METADATA
telealchemy-1.0.3.dist-info/WHEEL
telealchemy-1.0.3.dist-info/top_level.txt
telealchemy-1.0.3.dist-info/RECORD
